{"time": 2876, "memory": 195452, "problem": {"pid": "B3665", "title": "小清新数据结构题", "difficulty": 2, "type": "B"}, "sourceCodeLength": 555, "submitTime": 1728033160, "language": 28, "user": {"uid": 1054015, "name": "OP03_2", "avatar": "https://cdn.luogu.com.cn/upload/usericon/1054015.png", "slogan": "zorr noob lv250||https://atcoder.jp/users/cmq2014", "isAdmin": false, "isBanned": false, "color": "Red", "ccfLevel": 4, "xcpcLevel": 0, "background": "https://cdn.luogu.com.cn/upload/image_hosting/q28gw6j3.png"}, "id": 179974115, "status": 12, "enableO2": true, "score": 100, "detail": {"compileResult": {"success": true, "opt2": false}, "judgeResult": {"finishedCaseCount": 4, "status": 0, "time": 0, "memory": 0, "score": 0}, "version": 400}, "sourceCode": "#include<bits/stdc++.h>\r\n#define ull unsigned long long\r\nusing namespace std;\r\ninline ull read(){\r\n    ull x=0,f=1;\r\n    char ch=getchar();\r\n    while(ch<'0'||ch>'9'){if(ch=='-')f=-1;ch=getchar();}\r\n    while(ch>='0'&&ch<='9')x=x*10+ch-'0',ch=getchar();\r\n    return x*f;\r\n}\r\nconst ull N=4e6+5;\r\null n,m,ans;\r\nvector<ull> a[N];\r\nint main(void){\r\n\tn=read(),m=read();\r\n\tfor(ull i=1,s;i<=n;i++){\r\n\t\ts=read();\r\n\t\tfor(ull j=1,w;j<=s;j++)w=read(),a[i].push_back(w);\r\n\t}\r\n\tfor(ull i=1,x,y;i<=m;i++)x=read(),y=read(),ans^=a[x][y-1];\r\n\tcout<<ans;\r\n\treturn false;\r\n}", "_detail_requested": true, "_cached_at": "2026-06-05 19:03:13"}