{"time": 52, "memory": 836, "problem": {"pid": "P1528", "title": "切蛋糕【疑似错题】", "difficulty": 5, "type": "P"}, "sourceCodeLength": 1848, "submitTime": 1765873829, "language": 28, "user": {"uid": 1054015, "name": "OP03_2", "avatar": "https://cdn.luogu.com.cn/upload/usericon/1054015.png", "slogan": "zorr noob lv250||https://atcoder.jp/users/cmq2014", "isAdmin": false, "isBanned": false, "color": "Red", "ccfLevel": 4, "xcpcLevel": 0, "background": "https://cdn.luogu.com.cn/upload/image_hosting/q28gw6j3.png"}, "id": 253485507, "status": 12, "enableO2": true, "score": 100, "detail": {"compileResult": {"success": true, "opt2": false}, "judgeResult": {"finishedCaseCount": 12, "status": 0, "time": 0, "memory": 0, "score": 0}, "version": 400}, "sourceCode": "#include <bits/stdc++.h>\n#define int long long\n#define ull unsigned long long\n#define mk make_pair\n#define PII pair<int,int>\n#define NoAns puts(\"-1\");\n#define FOR(i,j,k) for(int i=(j);i<=(k);++i)\n#define ROF(i,j,k) for(int i=(j);i>=(k);--i)\n#define FOI(a,b) for(auto a : b)\n#define Yes puts(\"Yes\");\n#define No puts(\"No\");\n#define llinf 0x3f3f3f3f3f3f3f3f\n#define inf 0x3f3f3f3f\n#define ll long long\n#define snd second\n#define fst first\n#define il inline\n#define pb push_back\n#define CI const int\n#define cl(x) memset(x,0,sizeof x)\n#define cli(x) memset(x,0x3f,sizeof x)\n#define lowbit(x) (x&(-x))\n#define wh while\n#define gc() getchar()\n#define pc(x) putchar(x)\n#define NP namespace\n#define ls (k<<1)\n#define rs (k<<1|1)\nusing NP std;\nNP phigrOS\n{\n    il ll read()\n    {\n        ll x=0,f=1;char ch=gc();\n        wh(ch<'0'||ch>'9'){if(ch=='-')f=-1;ch=getchar();}\n        wh(ch>='0'&&ch<='9'){x=x*10+ch-'0';ch=gc();}\n        return x*f;\n    }\n    void write(ll x)\n    {\n        if(x<0)pc('-'),x=-x;\n        if(x>9)write(x/10);\n        pc(x%10+'0');\n    }\n    void writeln(ll x)\n    {\n        write(x);\n        puts(\"\");\n        return;\n    }\n}\nusing NP phigrOS;\nCI MAXN=1e5+5;\nint n,m,a[MAXN],b[MAXN],w,t,sum[MAXN],mid;\nbool dfs(int x, int l)\n{\n\tif(t-w<sum[mid])return false;\n\tif(x==0)return true;\n\tbool flag=0;\n\tFOR(i,l,n)\n\t{\n\t\tif(a[i]>=b[x])\n\t\t{\n\t\t\ta[i]-=b[x];\n\t\t\tif(a[i]<b[1])w+=a[i];\n\t\t\tif(b[x-1]==b[x])flag=dfs(x-1,i);\n\t\t\telse flag=dfs(x-1,1);\n\t\t\tif(a[i]<b[1])w-=a[i];\n\t\t\ta[i]+=b[x];\n\t\t\tif(flag)return true;\n\t\t}\n\t}\n\treturn false;\n}\nsigned main(void)\n{\n\tn=read();\n\tFOR(i,1,n)\n\t{\n\t\ta[i]=read(),t+=a[i];\t\n\t}\n\tm=read();\n\tFOR(i,1,m)\n\t{\n\t\tb[i]=read();\n\t}\n\tsort(b+1,b+m+1);\n\tFOR(i,1,m)\n\t{\n\t\tsum[i]=sum[i-1]+b[i];\n\t}\n\twh(sum[m]>t&&m)--m;\n\tint l=0,r=m;\n\twh(l<=r)\n\t{\n\t\tmid=(l+r)/2;\n\t\tif(dfs(mid,1))l=mid+1;\n\t\telse r=mid-1;\n\t}\n\twrite(l-1);\n\treturn false;\n}", "_detail_requested": true, "_cached_at": "2026-06-05 16:18:36"}