{"time": 70, "memory": 1140, "problem": {"pid": "P3817", "title": "小A的糖果", "difficulty": 2, "type": "P"}, "sourceCodeLength": 286, "submitTime": 1707130585, "language": 28, "user": {"uid": 1054015, "name": "OP03_2", "avatar": "https://cdn.luogu.com.cn/upload/usericon/1054015.png", "slogan": "zorr noob lv250||https://atcoder.jp/users/cmq2014", "isAdmin": false, "isBanned": false, "color": "Red", "ccfLevel": 4, "xcpcLevel": 0, "background": "https://cdn.luogu.com.cn/upload/image_hosting/q28gw6j3.png"}, "id": 146274683, "status": 12, "enableO2": true, "score": 100, "detail": {"compileResult": {"success": true, "opt2": false}, "judgeResult": {"finishedCaseCount": 12, "status": 0, "time": 0, "memory": 0, "score": 0}, "version": 400}, "sourceCode": "#include<bits/stdc++.h>\r\nusing namespace std;\r\nint main(void){\r\n\tlong long a[100005],l=0,n,x;\r\n    cin>>n>>x;\r\n    for(int i=1;i<=n;i++){\r\n        cin>>a[i];\r\n        if (a[i]+a[i-1]>x) {\r\n\t\t\tl+=a[i]+a[i-1]-x;\r\n\t\t\ta[i]=a[i]-(a[i-1]+a[i]-x);\r\n\t\t}\r\n    }\r\n    cout<<l;\r\n    return 0;\r\n}\r\n", "_detail_requested": true, "_cached_at": "2026-06-05 17:34:31"}