{"time": 2065, "memory": 2016, "problem": {"pid": "P9117", "title": "[春季测试 2023] 涂色游戏", "difficulty": 2, "type": "P"}, "sourceCodeLength": 498, "submitTime": 1721546704, "language": 28, "user": {"uid": 1054015, "name": "OP03_2", "avatar": "https://cdn.luogu.com.cn/upload/usericon/1054015.png", "slogan": "zorr noob lv250||https://atcoder.jp/users/cmq2014", "isAdmin": false, "isBanned": false, "color": "Red", "ccfLevel": 4, "xcpcLevel": 0, "background": "https://cdn.luogu.com.cn/upload/image_hosting/q28gw6j3.png"}, "id": 167571471, "status": 12, "enableO2": true, "score": 100, "detail": {"compileResult": {"success": true, "opt2": false}, "judgeResult": {"finishedCaseCount": 20, "status": 0, "time": 0, "memory": 0, "score": 0}, "version": 400}, "sourceCode": "#include<bits/stdc++.h>\r\nusing namespace std;\r\nconst int MAXN=1e+5+5;\r\nstruct node{\r\n\tint c,p;\r\n}h[MAXN],s[MAXN];\r\nint q,n,m,t,o,x,c;\r\nint main(void){\r\n\tcin>>t;\r\n\twhile(t--){\r\n\t\tmemset(h,0,sizeof(h));\r\n\t\tmemset(s,0,sizeof(s));\r\n\t\tcin>>n>>m>>q;\r\n\t\tfor(int i=1;i<=q;i++){\r\n\t\t\tcin>>o>>x>>c;\r\n\t\t\tif(o)s[x].c=c,s[x].p=i;\r\n\t\t\telse h[x].c=c,h[x].p=i;\r\n\t\t}for(int i=1;i<=n;i++){\r\n\t\t\tfor(int j=1;j<=m;j++){\r\n\t\t\t\tcout<<((h[i].p>s[j].p)?(h[i].c):(s[j].c))<<' ';\r\n\t\t\t}cout<<\"\\n\";\r\n\t\t}\r\n\t}\r\n    return false;\r\n}", "_detail_requested": true, "_cached_at": "2026-06-05 17:30:52"}